acamodels/__init__.py
acamodels/_basemodels.py
acamodels/_internals.py
acamodels/aca_base.py
acamodels/archive_file.py
acamodels/identification.py
acamodels-0.5.3.dist-info/LICENSE
acamodels-0.5.3.dist-info/WHEEL
acamodels-0.5.3.dist-info/METADATA
acamodels-0.5.3.dist-info/RECORD
