Metadata-Version: 2.1
Name: acamodels
Version: 0.5.3
Summary: Datamodels based on pydantic used in Python tools developed at Aarhus City Archives.
Home-page: https://www.aarhusstadsarkiv.dk/
License: GPL-3.0
Author: Nina Jensen
Author-email: jnik@aarhus.dk
Maintainer: Aarhus Stadsarkiv
Maintainer-email: stadsarkiv@aarhus.dk
Requires-Python: >=3.8,<4.0
Classifier: License :: OSI Approved :: GNU General Public License v3 (GPLv3)
Classifier: Programming Language :: Python :: 3
Classifier: Programming Language :: Python :: 3.8
Classifier: Programming Language :: Python :: 3.9
Requires-Dist: pydantic (>=1.6,<2.0)
